minimal_server/__init__.py
minimal_server/minimal_server.py
Minimal_Server-1.0.1.dist-info/LICENSE
Minimal_Server-1.0.1.dist-info/METADATA
Minimal_Server-1.0.1.dist-info/WHEEL
Minimal_Server-1.0.1.dist-info/top_level.txt
Minimal_Server-1.0.1.dist-info/RECORD
