Metadata-Version: 2.1
Name: Minimal-Server
Version: 1.0.1
Summary: Serve a python object through a simple socket; supports multiple connections.
Home-page: https://github.com/soldni/MinimalServer
Author: Luca Soldaini
Author-email: luca@soldaini.net
License: MIT License
Platform: UNKNOWN
Classifier: Development Status :: 5 - Production/Stable
Classifier: Intended Audience :: Developers
Classifier: Intended Audience :: Science/Research
Classifier: License :: OSI Approved :: MIT License
Classifier: Operating System :: OS Independent
Classifier: Programming Language :: Python :: 2
Classifier: Programming Language :: Python :: 3
Classifier: Topic :: System :: Networking
License-File: LICENSE
